berglas/__init__.py
berglas/auto.py
berglas/constants.py
berglas/exceptions.py
berglas/resolver.py
berglas/runtime.py
berglas-0.3.1.dist-info/LICENSE
berglas-0.3.1.dist-info/METADATA
berglas-0.3.1.dist-info/WHEEL
berglas-0.3.1.dist-info/top_level.txt
berglas-0.3.1.dist-info/RECORD
