Metadata-Version: 2.1
Name: berglas
Version: 0.3.1
Summary: Berglas Python Library
Home-page: https://github.com/maroux/berglas-python
Author: Aniruddha Maru
Maintainer: Aniruddha Maru
Maintainer-email: aniruddhamaru@gmail.com
License: Apache Software License (Apache License 2.0)
Keywords: secrets gcs gcp
Classifier: Natural Language :: English
Classifier: Development Status :: 3 - Alpha
Classifier: Intended Audience :: Developers
Classifier: Intended Audience :: System Administrators
Classifier: Topic :: Software Development :: Libraries :: Python Modules
Classifier: Programming Language :: Python
Classifier: Programming Language :: Python :: 3.6
Classifier: Programming Language :: Python :: 3.7
Classifier: Programming Language :: Python :: 3.9
Classifier: License :: OSI Approved :: Apache Software License
Requires-Python: >=3.6
License-File: LICENSE
Requires-Dist: pycryptodome
Requires-Dist: google-api-python-client (>=2)
Requires-Dist: google-cloud-storage (>=2)
Requires-Dist: google-cloud-kms (>=2)
Provides-Extra: dev
Requires-Dist: flake8 ; extra == 'dev'
Provides-Extra: publish
Requires-Dist: twine ; extra == 'publish'
Requires-Dist: wheel ; extra == 'publish'
Provides-Extra: test
Requires-Dist: pytest ; extra == 'test'
Requires-Dist: flake8 ; extra == 'test'
Requires-Dist: mypy ; extra == 'test'
Requires-Dist: ipdb ; extra == 'test'
Requires-Dist: coverage ; extra == 'test'
Requires-Dist: coveralls ; extra == 'test'
Requires-Dist: pytest-cov ; extra == 'test'
Requires-Dist: black ; extra == 'test'
